dvid_point_cloud/__init__.py
dvid_point_cloud/client.py
dvid_point_cloud/neuroglancer.py
dvid_point_cloud/parse.py
dvid_point_cloud/sampling.py
dvid_point_cloud-0.1.3.dist-info/licenses/LICENSE
dvid_point_cloud-0.1.3.dist-info/METADATA
dvid_point_cloud-0.1.3.dist-info/WHEEL
dvid_point_cloud-0.1.3.dist-info/top_level.txt
dvid_point_cloud-0.1.3.dist-info/RECORD
