Metadata-Version: 2.4
Name: dvid-point-cloud
Version: 0.1.3
Summary: Library for creating point clouds for sparse volumes within DVID
Author-email: William Katz <katzw@hhmi.org>
License: BSD-3-Clause
Project-URL: Homepage, https://github.com/JaneliaSciComp/dvid-point-cloud
Classifier: Programming Language :: Python :: 3
Classifier: License :: OSI Approved :: BSD License
Classifier: Operating System :: OS Independent
Requires-Python: >=3.7
License-File: LICENSE
Requires-Dist: requests>=2.25.0
Requires-Dist: numpy>=1.19.0
Requires-Dist: pandas>=1.2.0
Provides-Extra: dev
Requires-Dist: pytest>=6.0.0; extra == "dev"
Requires-Dist: requests-mock>=1.9.0; extra == "dev"
Requires-Dist: pytest-cov>=2.11.0; extra == "dev"
Requires-Dist: flake8>=3.8.0; extra == "dev"
Requires-Dist: mypy>=0.790; extra == "dev"
Dynamic: license-file
